vizedax/__init__.py
vizedax/datagod.py
vizedax-1.0.6.dist-info/LICENSE.txt
vizedax-1.0.6.dist-info/METADATA
vizedax-1.0.6.dist-info/WHEEL
vizedax-1.0.6.dist-info/top_level.txt
vizedax-1.0.6.dist-info/RECORD
