Metadata-Version: 2.1
Name: vizedax
Version: 1.0.6
Summary: EDA, Cleaning and Visualizations in an Instant!
Home-page: https://github.com/Shreyas-Madhav/Vizeda
Author: Shreyas Madhav AV
Author-email: shreyas.madhav@gmail.com
Project-URL: Repository, https://github.com/Shreyas-Madhav/Vizeda
Classifier: Programming Language :: Python :: 3
Classifier: License :: OSI Approved :: MIT License
Classifier: Operating System :: OS Independent
Requires-Python: >=3.6
License-File: LICENSE.txt
